themis.finals.api.auth-1.0.0-py2.7-nspkg.pth
themis/finals/api/auth/__about__.py
themis/finals/api/auth/__init__.py
themis.finals.api.auth-1.0.0.dist-info/DESCRIPTION.rst
themis.finals.api.auth-1.0.0.dist-info/METADATA
themis.finals.api.auth-1.0.0.dist-info/RECORD
themis.finals.api.auth-1.0.0.dist-info/WHEEL
themis.finals.api.auth-1.0.0.dist-info/metadata.json
themis.finals.api.auth-1.0.0.dist-info/namespace_packages.txt
themis.finals.api.auth-1.0.0.dist-info/top_level.txt
