Metadata-Version: 2.0
Name: themis.finals.api.auth
Version: 1.0.0
Summary: Themis Finals API authentication helpers
Home-page: https://github.com/aspyatkin/themis-finals-api-auth-py
Author: Alexander Pyatkin
Author-email: aspyatkin@gmail.com
License: MIT
Platform: UNKNOWN
Requires-Dist: setuptools (>=0.8)
